{
  "categoria": "dominio",
  "dominio": "splendore",
  "pagina": 4,
  "indice_carta": 5,
  "nome": "EMISSARIO DIVINO",
  "testo": [
    "EMISSARIO DIVINO",
    "Specializzazione",
    "Devoto:",
    "Quando tirate i Dadi Preghiera, potete",
    "tirare un dado aggiuntivo e scartare il risultato",
    "più basso. Inoltre, potete usare il privilegio",
    "“Tocco Ristoratore” due volte invece di una per",
    "riposo lungo.",
    "DH MB 032 /270 |",
    "Daggerheart © Darrington Press 2025"
  ],
  "id_carta": "032/270",
  "tipo_carta": "specializzazione",
  "nome_abilita": [
    "Specializzazione Devoto"
  ]
}