{
  "categoria": "dominio",
  "dominio": "grazia",
  "pagina": 11,
  "indice_carta": 5,
  "nome": "padronanza DELL’ARCANO",
  "testo": [
    "7",
    "2",
    "Abilità",
    "padronanza DELL’ARCANO",
    "Quando 4 o più carte dominio nella vostra dotazione",
    "appartengono al dominio Arcano, ottenete i",
    "seguenti benefi ci:",
    "• Bonus +1 ai Tiri Incantesimo",
    "• Una volta per riposo, potete scambiare i risultati dei",
    "vostri Dadi Speranza e Paura.",
    "DH MB 095/270 |",
    "Daggerheart © Darrington Press 2025"
  ],
  "id_carta": "095/270",
  "soglia": "7",
  "livello": "2",
  "tipo_carta": "incantesimo",
  "nome_abilita": [
    "Arcano, ottenete i seguenti benefi ci"
  ]
}